malibu/__init__.py
malibu/command/__init__.py
malibu/command/module.py
malibu/command/builtins/__init__.py
malibu/command/builtins/config.py
malibu/command/builtins/help.py
malibu/config/__init__.py
malibu/config/configuration.py
malibu/database/__init__.py
malibu/database/dbmapper.py
malibu/database/dbtypeconv.py
malibu/design/__init__.py
malibu/design/borgish.py
malibu/design/brine.py
malibu/text/__init__.py
malibu/text/ascii.py
malibu/text/table.py
malibu/util/__init__.py
malibu/util/args.py
malibu/util/decorators.py
malibu/util/log.py
malibu/util/names.py
malibu/util/paths.py
malibu/util/scheduler.py
malibu-0.1.8.post9.data/scripts/jsontable
malibu-0.1.8.post9.dist-info/DESCRIPTION.rst
malibu-0.1.8.post9.dist-info/METADATA
malibu-0.1.8.post9.dist-info/RECORD
malibu-0.1.8.post9.dist-info/WHEEL
malibu-0.1.8.post9.dist-info/metadata.json
malibu-0.1.8.post9.dist-info/top_level.txt
malibu-0.1.8.post9.dist-info/zip-safe
