Metadata-Version: 2.0
Name: malibu
Version: 0.1.8.post9
Summary: maiome library of utilities - rev 0.1.8-9-402be4c
Home-page: https://glow.dev.ramcloud.io/maiome/malibu
Author: Sean Johnson
Author-email: sean.johnson@maio.me
License: Unlicense
Platform: UNKNOWN
Classifier: Development Status :: 4 - Beta
Classifier: License :: Public Domain
Classifier: Programming Language :: Python :: 2
Classifier: Programming Language :: Python :: 3
Classifier: Topic :: Software Development :: Libraries
Classifier: Topic :: Software Development :: Libraries :: Python Modules
Requires-Dist: dill
